src/__init__.py
src/github_flow.py
src/settings.py
src/commands/__init__.py
src/commands/feature_command.py
src/commands/hotfix_command.py
src/commands/release_command.py
src/utils/__init__.py
src/utils/branch.py
src/utils/bump_version.py
src/utils/config_file.py
src/utils/git.py
src/utils/pull_request.py
src/utils/release.py
src/utils/shell.py
github_flow-0.2.dist-info/LICENSE
github_flow-0.2.dist-info/METADATA
github_flow-0.2.dist-info/WHEEL
github_flow-0.2.dist-info/entry_points.txt
github_flow-0.2.dist-info/top_level.txt
github_flow-0.2.dist-info/RECORD
