Metadata-Version: 2.1
Name: github-flow
Version: 0.2
Summary: A git extension which provides commands for working according Git-Flow easily & safely in your repository.
Home-page: https://github.com/ShakedBraimok/github-flow
Author: ShakedBraimok (Shaked Braimok Yosef)
Author-email: shaked.braimok.yosef@gmail.com
License: GPL
Platform: UNKNOWN
Requires-Dist: click (>=6.7)
Requires-Dist: PyYAML (>=3.12)
